jrpc/__init__.py
async_jrpc-1.0.0.dist-info/LICENSE
async_jrpc-1.0.0.dist-info/WHEEL
async_jrpc-1.0.0.dist-info/METADATA
async_jrpc-1.0.0.dist-info/RECORD
